README.txt
setup.py
c2/__init__.py
c2.sample.csvworkflow.egg-info/PKG-INFO
c2.sample.csvworkflow.egg-info/SOURCES.txt
c2.sample.csvworkflow.egg-info/dependency_links.txt
c2.sample.csvworkflow.egg-info/entry_points.txt
c2.sample.csvworkflow.egg-info/namespace_packages.txt
c2.sample.csvworkflow.egg-info/not-zip-safe
c2.sample.csvworkflow.egg-info/requires.txt
c2.sample.csvworkflow.egg-info/top_level.txt
c2/sample/__init__.py
c2/sample/csvworkflow/__init__.py
c2/sample/csvworkflow/_tests.py
c2/sample/csvworkflow/configure.zcml
c2/sample/csvworkflow/version.txt
c2/sample/csvworkflow/profiles/default/metadata.xml
c2/sample/csvworkflow/profiles/default/workflows.xml
c2/sample/csvworkflow/profiles/default/workflow_csv/c2.sample.csvworkflow.csv
c2/sample/csvworkflow/tests/WFtest.py
c2/sample/csvworkflow/tests/__init__.py
c2/sample/csvworkflow/tests/base.py
c2/sample/csvworkflow/tests/testSetup.py
docs/HISTORY.txt
docs/INSTALL.txt
docs/LICENSE.GPL
docs/LICENSE.txt