Metadata-Version: 1.0
Name: c2.sample.csvworkflow
Version: 1.1
Summary: c2.sample.csvworkflow is sample application using by collective.wtf.
Home-page: http://svn.plone.org/svn/collective/
Author: Hironobu Manaka
Author-email: tokinotsubasa@gmail.com
License: GPL
Keywords: plone,workflow
Platform: UNKNOWN
Classifier: Framework :: Plone
Classifier: Programming Language :: Python
